{
  "_meta": {
    "what": "#47 флот-V3 config-diff: 23 крутилки воркера (knobs.default под впрыснутым V3-env) vs reference/fleet-live-config.json. Один env впрыснут во все 5 (Персиваль/Галахад/Борс/Ланселот/Гавейн) → дамп общий.",
    "base": "reference/fleet-live-config.json (Живой V3)",
    "mode": "dry-run cloud (BYBIT_DEMO=1, LIVE_TRADING_ENABLED=0)",
    "captured": "2026-07-16"
  },
  "worker": {
    "RISK_PCT_PER_LEG": 2.5,
    "RISK_PCT_ALARM": 0.65,
    "KILLSWITCH_DD": 0.7,
    "ALARM_DD": 0.4,
    "CONCURRENCY_CAP": 16,
    "MAX_LEVERAGE": 5,
    "REFINANCE_SPLIT": 0.5,
    "WORKING_START": 10000.0,
    "CUSHION_START": 10000.0,
    "STOP_FIB": 1.0,
    "SL_TRIGGER_BY": "LastPrice",
    "SHORTS_ENABLED": false,
    "EMA_FILTER_ENABLED": false,
    "REANCHOR_AFTER_SCALP": true,
    "PAUSE_ENABLED": false,
    "WARM_ON_START": true,
    "WARM_MAX_AGE_BARS": 144,
    "RUNNER_TP_HOLD": true,
    "LEG2_EXT": 0.618,
    "DOUBLE_DIP_ENABLED": false,
    "DOUBLE_DIP_TOL": 0.04,
    "TRAIL_ENABLED": true,
    "TRAIL_R": 0.4
  },
  "expected": {
    "RISK_PCT_PER_LEG": 2.5,
    "RISK_PCT_ALARM": 0.65,
    "KILLSWITCH_DD": 0.7,
    "ALARM_DD": 0.4,
    "CONCURRENCY_CAP": 16,
    "MAX_LEVERAGE": 5,
    "REFINANCE_SPLIT": 0.5,
    "WORKING_START": 10000,
    "CUSHION_START": 10000,
    "STOP_FIB": 1.0,
    "SL_TRIGGER_BY": "LastPrice",
    "SHORTS_ENABLED": false,
    "EMA_FILTER_ENABLED": false,
    "REANCHOR_AFTER_SCALP": true,
    "PAUSE_ENABLED": false,
    "WARM_ON_START": true,
    "WARM_MAX_AGE_BARS": 144,
    "RUNNER_TP_HOLD": true,
    "LEG2_EXT": 0.618,
    "DOUBLE_DIP_ENABLED": false,
    "DOUBLE_DIP_TOL": 0.04,
    "TRAIL_ENABLED": true,
    "TRAIL_R": 0.4
  },
  "drift": []
}